aivoicegen/__init__.py
aivoicegen/__main__.py
aivoicegen/app.py
aivoicegen/cli.py
aivoicegen/config.py
aivoicegen/database.py
aivoicegen/providers.py
aivoicegen/routes.py
aivoicegen/static/index.html
aivoicegen-1.5.2.dist-info/licenses/LICENSE
aivoicegen-1.5.2.dist-info/METADATA
aivoicegen-1.5.2.dist-info/WHEEL
aivoicegen-1.5.2.dist-info/entry_points.txt
aivoicegen-1.5.2.dist-info/top_level.txt
aivoicegen-1.5.2.dist-info/RECORD
