Metadata-Version: 2.4
Name: aivoicegen
Version: 1.5.2
Summary: AI-powered Text-to-Speech web application with multiple provider support
Author: Michael Jabbour
Maintainer: Michael Jabbour
License: MIT License
Project-URL: Homepage, https://github.com/michaeljabbour/aivoicegen
Project-URL: Documentation, https://github.com/michaeljabbour/aivoicegen#readme
Project-URL: Repository, https://github.com/michaeljabbour/aivoicegen
Project-URL: Bug Tracker, https://github.com/michaeljabbour/aivoicegen/issues
Project-URL: Source Code, https://github.com/michaeljabbour/aivoicegen
Keywords: text-to-speech,tts,ai,voice,speech-synthesis,openai,elevenlabs,google-cloud,gemini,flask,web-app
Classifier: Development Status :: 5 - Production/Stable
Classifier: Intended Audience :: Developers
Classifier: Intended Audience :: End Users/Desktop
Classifier: Operating System :: OS Independent
Classifier: Programming Language :: Python :: 3
Classifier: Programming Language :: Python :: 3.8
Classifier: Programming Language :: Python :: 3.9
Classifier: Programming Language :: Python :: 3.10
Classifier: Programming Language :: Python :: 3.11
Classifier: Programming Language :: Python :: 3.12
Classifier: Topic :: Multimedia :: Sound/Audio :: Speech
Classifier: Topic :: Software Development :: Libraries :: Python Modules
Classifier: Topic :: Internet :: WWW/HTTP :: WSGI :: Application
Classifier: Environment :: Web Environment
Classifier: Framework :: Flask
Requires-Python: >=3.8
License-File: LICENSE
Requires-Dist: openai>=1.3.0
Requires-Dist: flask==2.3.3
Requires-Dist: flask-cors==4.0.2
Requires-Dist: pydub==0.25.1
Requires-Dist: requests>=2.32.3
Requires-Dist: google-cloud-texttospeech>=2.14.0
Requires-Dist: google-generativeai>=0.1.0rc1
Requires-Dist: elevenlabs>=1.0.0
Requires-Dist: python-dotenv>=1.0.0
Provides-Extra: dev
Requires-Dist: pytest>=7.0.0; extra == "dev"
Requires-Dist: pytest-cov>=4.0.0; extra == "dev"
Requires-Dist: black>=23.0.0; extra == "dev"
Requires-Dist: flake8>=6.0.0; extra == "dev"
Requires-Dist: mypy>=1.0.0; extra == "dev"
Dynamic: license-file
